pyhttpfs/__init__.py
pyhttpfs/__main__.py
pyhttpfs/_logging.py
pyhttpfs/routing.py
pyhttpfs/assets/icons.json
pyhttpfs/assets/static/css/explorer.css
pyhttpfs/core/args.py
pyhttpfs/core/config.py
pyhttpfs/core/icons.py
pyhttpfs/templates/base.html
pyhttpfs/templates/explorer.html
pyhttpfs/templates/errors/404.html
pyhttpfs-1.0.9.dist-info/LICENSE.txt
pyhttpfs-1.0.9.dist-info/METADATA
pyhttpfs-1.0.9.dist-info/WHEEL
pyhttpfs-1.0.9.dist-info/entry_points.txt
pyhttpfs-1.0.9.dist-info/top_level.txt
pyhttpfs-1.0.9.dist-info/RECORD
